{
  "type": "entry",
  "author": {
    "type": "card",
    "name": "Brian Ellin",
    "url": "http://brianellin.com/",
    "photo": "https://www.gravatar.com/avatar/2b5b1bac34d7d1bd326d51fae39464a4?d=404"
  },
  "url": "http://brianellin.com/",
  "published": "2007-10-12T22:05:59-07:00",
  "content": {
    "html": "<p>Fatal error: Call to a member function getArg() on a non-object in /home/xxx/xxx/xxx/wp-content/plugins/openid/Auth/OpenID/Consumer.php on line 2001</p>\n\n<p>Any ideas on how to fix this one?  wp 2.3 &amp; php 5.2.2</p>\n",
    "text": ""
  },
  "wm-id": "13699",
  "wm-property": "in-reply-to",
  "in-reply-to": "https://willnorris.com/2007/10/plugin-updates/"
}