{
  "type": "entry",
  "author": {
    "type": "card",
    "name": "Terrell Russell",
    "url": "",
    "photo": "https://www.gravatar.com/avatar/112fb685c2402e6fce3c1f01aa5cac5f?s=256&d=404"
  },
  "url": "",
  "published": "2007-10-24T13:08:07-07:00",
  "content": {
    "html": "<p>This is exactly what is needed.  Strong defaults with good explanations.  Thanks.  Keep the analysis coming.</p>\n\n<p>Terrell</p>\n",
    "text": ""
  },
  "wm-id": "14093",
  "wm-property": "in-reply-to",
  "in-reply-to": "https://willnorris.com/2007/10/wp-openid-intelligent-defaults/"
}