{
  "type": "entry",
  "author": {
    "type": "card",
    "name": "Will Norris",
    "url": "http://will.norris.name",
    "photo": "https://www.gravatar.com/avatar/2025929025b4492c58961f28cc4ed93d?d=404"
  },
  "url": "http://will.norris.name",
  "published": "2008-10-15T19:15:02-07:00",
  "content": {
    "html": "@Nilton: I assume you meant WPMu?  Yes, it works fine on the multi-user version of WordPress, as can be seen at http://blogs.gnome.org/",
    "text": ""
  },
  "wm-id": "25708",
  "wm-property": "in-reply-to",
  "in-reply-to": "https://willnorris.com/2008/10/wordpress-openid-v3/"
}