{
  "type": "entry",
  "author": {
    "type": "card",
    "name": "Asbed Bedrossian",
    "url": "",
    "photo": "https://www.gravatar.com/avatar/e0c5b10a8aa90e1a4777b6d6d97ba736?d=404"
  },
  "url": "",
  "published": "2010-01-27T07:40:51-08:00",
  "content": {
    "html": "<p>Awesome news for the community, can't wait to see the fruits of your team's labor. In the meantime I hope Elizabeth puts up with the second round in the bay area... :)</p>\n",
    "text": ""
  },
  "wm-id": "40587",
  "wm-property": "in-reply-to",
  "in-reply-to": "https://willnorris.com/2010/01/going-to-google/"
}