{
  "type": "entry",
  "author": {
    "type": "card",
    "name": "Dentaku &raquo; Blog Archiv &raquo; Neu hier: OpenID",
    "url": "http://wazong.de/blog/2007/12/02/neu-hier-openid/"
  },
  "url": "http://wazong.de/blog/2007/12/02/neu-hier-openid/",
  "published": "2007-12-02T18:50:51-08:00",
  "content": {
    "html": "<p>[...] einer OpenID-Anmeldung ausr체sten. Die Wordpress-Installation f체r dieses Blog hat jetzt schon das WP-OpenID-Plugin von Will Norris. Wer mit einer OpenID-f채higen URL kommentiert, der kann sich die Eingaben f체r [...]</p>\n",
    "text": ""
  },
  "wm-id": "15618",
  "wm-property": "mention-of",
  "mention-of": "https://willnorris.com/2007/11/wp-openid-20-released/"
}